cutview/__init__.py
cutview/cutview.kv
cutview/cutview.py
cutview/dropdowns.py
cutview/filedisplay.py
cutview/functions.py
cutview/homescreen.py
cutview/logger.py
cutview/marker.py
cutview/markerwidth.py
cutview/multimarker.py
cutview/multitransect.py
cutview/netcdfconfig.py
cutview/plotpopup.py
cutview/project_file_printer.py
cutview/singletransect.py
cutview-0.2.10.dist-info/LICENSE.txt
cutview-0.2.10.dist-info/METADATA
cutview-0.2.10.dist-info/WHEEL
cutview-0.2.10.dist-info/RECORD
