Metadata-Version: 2.1
Name: cutview
Version: 0.2.10
Summary: CutView is a GUI for getting pixel data from images and data values from NetCDF files along linear transects.
Home-page: https://github.com/rchartra/CutView
License: GPL-3.0-or-later
Keywords: NetCDF,GUI
Author: rchartra
Author-email: rchartra@uw.edu
Requires-Python: >=3.9,<4.0
Classifier: Intended Audience :: Science/Research
Classifier: License :: OSI Approved :: GNU General Public License v3 or later (GPLv3+)
Classifier: Operating System :: OS Independent
Classifier: Programming Language :: Python
Classifier: Programming Language :: Python :: 3
Classifier: Programming Language :: Python :: 3.9
Classifier: Programming Language :: Python :: 3.10
Classifier: Programming Language :: Python :: 3.11
Classifier: Programming Language :: Python :: 3.12
Requires-Dist: Cython (>=3.0.10,<4.0.0)
Requires-Dist: Kivy (>=2.3.0,<3.0.0)
Requires-Dist: img2pdf (>=0.5.1,<0.6.0)
Requires-Dist: matplotlib (>=3.9.0,<4.0.0)
Requires-Dist: netCDF4 (>=1.7.1,<2.0.0)
Requires-Dist: numpy (>=2.0.0,<3.0.0)
Requires-Dist: opencv-python (>=4.10.0.84,<5.0.0.0)
Requires-Dist: pandas (>=2.2.2,<3.0.0)
Requires-Dist: scipy (>=1.13.1,<2.0.0)
Requires-Dist: xarray (>=2024.6.0,<2025.0.0)
Project-URL: Documentation, https://cutview.readthedocs.io/en/latest/index.html
Project-URL: Repository, https://github.com/rchartra/CutView
